graphconstructor/__init__.py
graphconstructor/adapters.py
graphconstructor/graph.py
graphconstructor/importers.py
graphconstructor/operators/__init__.py
graphconstructor/operators/base.py
graphconstructor/operators/disparity.py
graphconstructor/operators/doubly_stochastic.py
graphconstructor/operators/knn_selector.py
graphconstructor/operators/locally_adaptive_sparsification.py
graphconstructor/operators/marginal_likelihood.py
graphconstructor/operators/noise_corrected.py
graphconstructor/operators/weight_threshold.py
graphconstructor/pipeline.py
graphconstructor/types.py
graphconstructor/utils.py
graphconstructor/visualization/__init__.py
graphconstructor/visualization/graph_statistics.py
graphconstructor/visualization/network_plots_nx.py
graphconstructor-0.2.2.dist-info/METADATA
graphconstructor-0.2.2.dist-info/WHEEL
graphconstructor-0.2.2.dist-info/licenses/LICENSE
graphconstructor-0.2.2.dist-info/RECORD
