Metadata-Version: 2.4
Name: graphconstructor
Version: 0.2.2
Summary: Python library for graph construction from similarity or distance metrics
License: MIT
License-File: LICENSE
Author: Florian Huber
Author-email: florian.huber@hs-duesseldorf.de
Requires-Python: >=3.10,<3.14
Classifier: Development Status :: 4 - Beta
Classifier: Intended Audience :: Developers
Classifier: Intended Audience :: Education
Classifier: Intended Audience :: Science/Research
Classifier: License :: OSI Approved :: MIT License
Classifier: Natural Language :: English
Classifier: Programming Language :: Python :: 3
Classifier: Programming Language :: Python :: 3.10
Classifier: Programming Language :: Python :: 3.11
Classifier: Programming Language :: Python :: 3.12
Classifier: Programming Language :: Python :: 3.13
Requires-Dist: matplotlib (>=3.8.0)
Requires-Dist: networkx (>3.4.0)
Requires-Dist: numpy (>=2.0.0)
Requires-Dist: pandas (>=2.1.1)
Requires-Dist: scipy (>=1.14.0)
Project-URL: Repository, https://github.com/matchms/graphconstructor
